{
    "$schema": "https://raw.githubusercontent.com/molanp/BingHomepageQuizData/refs/heads/main/schema.json",
    "date": "2026/06/14",
    "result": [
        {
            "question": "法国与荷兰均有绿头鸭栖息的生境是何处？",
            "answer": "A. 沼泽地",
            "choices": {
                "A. 沼泽地": 603,
                "B. 珊瑚礁": 182,
                "C. 干旱平原": 83
            }
        },
        {
            "question": "雄性与雌性绿头鸭有何显著区别？",
            "answer": "C. 头部颜色",
            "choices": {
                "C. 头部颜色": 316,
                "A. 喙的大小": 185,
                "B. 翼长": 108
            }
        },
        {
            "question": "雌性绿头鸭在春季通常在哪里筑巢？",
            "answer": "B. 隐秘庇护所",
            "choices": {
                "B. 隐秘庇护所": 349,
                "C. 树冠": 100,
                "A. 开阔水域": 147
            }
        }
    ]
}