{
    "$schema": "https://raw.githubusercontent.com/molanp/BingHomepageQuizData/refs/heads/main/schema.json",
    "date": "2025-10-15",
    "result": [
        {
            "question": "紫蜡蘑的特征是什么？",
            "answer": "它以其鲜艳的紫色而闻名。",
            "choices": {
                "它是生物发光的。": 1622,
                "它以其鲜艳的紫色而闻名。": 4634,
                "它仅生长在橡树上。": 249,
                " 它以其鲜艳的紫色而闻名。": 1
            }
        },
        {
            "question": "紫蜡蘑通常生长在哪种栖息地中？",
            "answer": "林地和森林",
            "choices": {
                "开阔的草原": 356,
                "林地和森林": 5352,
                "沙漠和干旱地区。": 499,
                " 林地和森林": 2
            }
        },
        {
            "question": "紫蜡蘑的主要生态作用是什么？",
            "answer": "菌根真菌",
            "choices": {
                "它作为一种光合作用植物。": 642,
                "菌根真菌": 4740,
                "它充当小型昆虫的捕食者。": 747
            }
        }
    ]
}