{
    "$schema": "https://raw.githubusercontent.com/molanp/BingHomepageQuizData/refs/heads/main/schema.json",
    "date": "2026/07/18",
    "result": [
        {
            "question": "建造拉科茨桥使用了哪种类型的岩石？",
            "answer": "B. 玄武岩",
            "choices": {
                "A. 花岗岩": 8241,
                "B. 玄武岩": 6545,
                "C. 砂岩": 1417
            }
        },
        {
            "question": "拉科茨桥位于德国的哪个州？",
            "answer": "A. 萨克森",
            "choices": {
                "A. 萨克森": 5979,
                "B. 巴伐利亚": 4262,
                "C. 黑塞": 1137
            }
        },
        {
            "question": "为何禁止行人通行拉科茨桥？",
            "answer": "A. 脆弱结构",
            "choices": {
                "B. 私人财产": 1817,
                "C. 野生动物栖息地": 3313,
                "A. 脆弱结构": 5849
            }
        }
    ]
}